vaultinum_ts/__init__.py
vaultinum_ts/__main__.py
vaultinum_ts/__version__.py
vaultinum_ts/vaultinum_ts.py
vaultinum_ts-0.0.3.dist-info/METADATA
vaultinum_ts-0.0.3.dist-info/WHEEL
vaultinum_ts-0.0.3.dist-info/licenses/LICENSE
vaultinum_ts-0.0.3.dist-info/RECORD
