Metadata-Version: 2.3
Name: vaultinum_ts
Version: 0.0.3
Summary: Client for Vaultinum's timestamping service.
Project-URL: Homepage, https://github.com/vaultinum/vaultinum-timestamping-sdk
Project-URL: Documentation, https://docs.vaultinum.com
Project-URL: Issues, https://github.com/vaultinum/vaultinum-timestamping-sdk/issues
Author-email: Vaultinum <contact@vaultinum.com>
License: MIT License
License-File: LICENSE
Keywords: RFC3161,timestamping,vaultinum
Classifier: Development Status :: 5 - Production/Stable
Classifier: Intended Audience :: Developers
Classifier: License :: OSI Approved :: MIT License
Requires-Python: >=3.8
Requires-Dist: requests>=2.31.0
Requires-Dist: rfc3161ng>=2.1.3
